callbook/__init__.py
callbook/call.py
callbook/database.py
callbook/debuger.py
callbook/main.py
callbook/font/Inconsolata.ttf
callbook/gui/CallStackView.py
callbook/gui/CommentEdit.py
callbook/gui/Document.py
callbook/gui/MainWindow.py
callbook/gui/SourceEdit.py
callbook/gui/__init__.py
callbook/gui/about.py
callbook/gui/openai_settings_dialog.py
callbook/gui/search_window.py
callbook/gui/source_file_path_dialog.py
callbook/gui/source_file_path_dialog.ui
callbook/image/Function.png
callbook/image/arrow-down.svg
callbook/image/arrow-up.svg
callbook/image/case-sensitive.svg
callbook/image/close.svg
callbook/image/comment.png
callbook/image/deepseek.png
callbook/image/groq.png
callbook/image/logo.png
callbook/image/regex.svg
callbook/image/setting-svgrepo-com.svg
callbook/image/whole-word.svg
callbook-0.0.7.dist-info/METADATA
callbook-0.0.7.dist-info/WHEEL
callbook-0.0.7.dist-info/entry_points.txt
callbook-0.0.7.dist-info/top_level.txt
callbook-0.0.7.dist-info/RECORD
