Metadata-Version: 2.4
Name: callbook
Version: 0.0.7
Summary: Show the callstacks
Author-email: Jun Chen <junc76@gmail.com>
Requires-Python: >=3.9
Requires-Dist: PyQt5
Requires-Dist: qscintilla
Requires-Dist: PyQtWebEngine
Requires-Dist: markdown
Requires-Dist: pygments
Requires-Dist: chardet
Requires-Dist: openai
